Workbook
Name HighlightActivities: 'Analytics Dashboard'!$G$5
Name HighlightActivities: 'Dispatch Automation'!$G$5
Name HighlightActivities: 'Expense Tracking'!$G$5
Name HighlightActivities: 'MAP Checklist'!$G$5
Name HighlightActivities: 'Smarter Extraction'!$G$5
Name HighlightActivities: 'To Do List'!$G$5
Name lstToDoHighlights: 'Settings & Calculations'!$E$5:$E$15
Name Print_Area_Reset: OFFSET('Analytics Dashboard'!$A:$H,0,0,COUNTA('Analytics Dashboard'!$B:$B)+5)
Name Print_Area_Reset: OFFSET('Dispatch Automation'!$A:$H,0,0,COUNTA('Dispatch Automation'!$B:$B)+5)
Name Print_Area_Reset: OFFSET('Expense Tracking'!$A:$H,0,0,COUNTA('Expense Tracking'!$B:$B)+5)
Name Print_Area_Reset: OFFSET('MAP Checklist'!$A:$H,0,0,COUNTA('MAP Checklist'!$B:$B)+5)
Name Print_Area_Reset: OFFSET('Smarter Extraction'!$A:$H,0,0,COUNTA('Smarter Extraction'!$B:$B)+5)
Name Print_Area_Reset: OFFSET('To Do List'!$A:$H,0,0,COUNTA('To Do List'!$B:$B)+5)
Name valHEnd: 'Settings & Calculations'!$C$18
Name valHStart: 'Settings & Calculations'!$C$17

Sheet To Do List
B2: Project To Do List
B4: To be completed by | C4: Overall Progress | E4: Deadline | F4: Days left | G4: Highlight Activities
B5: Andres Gomez | C5: =SUM(tblToDoListMaster[Progress]) / COUNT(tblToDoListMaster[Progress]) -> 0.21944444 | E5: 46214 | F5: =E5-TODAY() & " days left" -> 22 days left | G5: This Week [15 Jun - 21 Jun]
B6: Automated Rate Confirmation Parser and Analytics Platform
B7: Activity | C7: Due By | D7: Budget | E7: Done | F7: Progress | G7: Notes
B8: Planning | C8: 46190 | D8: 0 | E8: YES | F8: 1
B9: Manual Assisted Parser | C9: 46204 | D9: 0 | F9: =SUM(tblToDoList1[Progress]) / COUNT(tblToDoList1[Progress]) -> 0.31666667
B10: Dispatch Automation | C10: 46210 | D10: 0 | F10: =SUM(tblToDoList2[Progress]) / COUNT(tblToDoList2[Progress]) -> 0
B11: Expense Tracking | C11: 46214 | D11: 0 | F11: =SUM(tblToDoList3[Progress]) / COUNT(tblToDoList3[Progress]) -> 0
B12: Analytics Dashboard | C12: 46217 | D12: 0 | F12: =SUM(tblToDoList4[Progress]) / COUNT(tblToDoList4[Progress]) -> 0
B13: Smarter Extraction | C13: 46228 | D13: 0 | F13: =SUM(tblToDoList5[Progress]) / COUNT(tblToDoList5[Progress]) -> 0

Sheet MAP Checklist
B2: Project To Do List
B4: To be completed by: | E4: Deadline: | F4: Days left: | G4: Highlight Activities
B5: Andres Gomez | E5: ='To Do List'!C9 -> 46204 | F5: =E5-TODAY() & " days left" -> 12 days left | G5: This Month [1 - 30, Jun]
B6: ='To Do List'!B9 -> Manual Assisted Parser
B7: Activity | C7: Due By | D7: Budget | E7: Done | F7: Progress | G7: Notes
B8: PDF Upload | C8: 46193 | D8: 0 | F8: 0.95 | G8: Streamlit App; Supabase DB
B9: Text Extraction | C9: 46191 | D9: 0 | F9: 0.95
B10: LLM/regex parsing into structured fields | C10: 46198 | D10: 0 | F10: 0
B11: Editable Form | C11: 46199 | D11: 0 | F11: 0
B12: Save to database | C12: 46203 | D12: 0 | F12: 0
B13: Copyable Driver Message | C13: 46204 | D13: 0 | F13: 0

Sheet Dispatch Automation
B2: Project To Do List
B4: To be completed by: | E4: Deadline: | F4: Days left: | G4: Highlight Activities
B5: Andres Gomez | E5: ='To Do List'!C10 -> 46210 | F5: =E5-TODAY() & " days left" -> 18 days left | G5: This Week [15 Jun - 21 Jun]
B6: ='To Do List'!B10 -> Dispatch Automation
B7: Activity | C7: Due By | D7: Budget | E7: Done | F7: Progress | G7: Notes
B8: Driver Table | C8: 46207 | D8: 0 | F8: 0
B9: Truck Table | C9: 46207 | D9: 0 | F9: 0
B10: Driver Email Selection | C10: 46205 | D10: 0 | F10: 0
B11: Email Template | C11: 46204 | D11: 0 | F11: 0
B12: Send Email Button | C12: 46208 | D12: 0 | F12: 0
B13: Sent-Message Log | C13: 46210 | D13: 0 | F13: 0

Sheet Expense Tracking
B2: Project To Do List
B4: To be completed by: | E4: Deadline: | F4: Days left: | G4: Highlight Activities
B5: Andres Gomez | E5: ='To Do List'!C11 -> 46214 | F5: =E5-TODAY() & " days left" -> 22 days left | G5: This Week [15 Jun - 21 Jun]
B6: ='To Do List'!B11 -> Expense Tracking
B7: Activity | C7: Due By | D7: Budget | E7: Done | F7: Progress | G7: Notes
B8: Diesel Input | C8: 46211 | D8: 0 | F8: 0
B9: Maintenance Input | C9: 46211 | D9: 0 | F9: 0
B10: Tolls/lumpers | C10: 46212 | D10: 0 | F10: 0
B11: Reciepts Upload | C11: 46212 | D11: 0 | F11: 0
B12: Associate expenses with truck and/or load | C12: 46214 | D12: 0 | F12: 0

Sheet Analytics Dashboard
B2: Project To Do List
B4: To be completed by: | E4: Deadline: | F4: Days left: | G4: Highlight Activities
B5: Andres Gomez | E5: ='To Do List'!C12 -> 46217 | F5: =E5-TODAY() & " days left" -> 25 days left | G5: This Week [15 Jun - 21 Jun]
B6: ='To Do List'!B12 -> Analytics Dashboard
B7: Activity | C7: Due By | D7: Budget | E7: Done | F7: Progress | G7: Notes
B8: Revenue By Truck | C8: 46215 | D8: 0 | F8: 0
B9: Rate per mile | C9: 46215 | D9: 0 | F9: 0
B10: Fuel cost per mule | C10: 46216 | D10: 0 | F10: 0
B11: Gross margin by load | C11: 46216 | D11: 0 | F11: 0
B12: Broker performance | C12: 46217 | D12: 0 | F12: 0
B13: Maintenance by Truck | C13: 46217 | D13: 0 | F13: 0

Sheet Smarter Extraction
B2: Project To Do List
B4: To be completed by: | E4: Deadline: | F4: Days left: | G4: Highlight Activities
B5: Andres Gomez | E5: ='To Do List'!C13 -> 46228 | F5: =E5-TODAY() & " days left" -> 36 days left | G5: This Week [15 Jun - 21 Jun]
B6: ='To Do List'!B13 -> Smarter Extraction
B7: Activity | C7: Due By | D7: Budget | E7: Done | F7: Progress | G7: Notes
B8: broker-specific parsing rules | C8: 46219 | D8: 0 | F8: 0
B9: confidence scores | C9: 46222 | D9: 0 | F9: 0
B10: flagged missing fields | C10: 46224 | D10: 0 | F10: 0
B11: duplicate load detection | C11: 46226 | D11: 0 | F11: 0
B12: OCR/scanned PDF support | C12: 46228 | D12: 0 | F12: 0 | G12: Not important

Sheet Settings & Calculations
B2: Highlight Settings
B4: The tables below store settings and calculations for the Highlight Activities drop down list. Any changes could result in errors or loss of functionality.
B5: No Highlight | E5: =B5 -> No Highlight
B6: Interval: | C6: Start: | D6: End: | E6: Due:
B7: This Week | C7: =TODAY()-WEEKDAY(TODAY(),2)+1 -> 46188 | D7: =C7+6 -> 46194 | E7: =B7&" ["&TEXT(C7,"d mmm")&" - "&TEXT(D7,"d mmm")&"]" -> This Week [15 Jun - 21 Jun]
B8: This Month | C8: =EOMONTH(TODAY(),-1)+1 -> 46174 | D8: =EDATE(C8,1)-1 -> 46203 | E8: =B8&" ["&TEXT(C8,"d")&" - "&TEXT(D8,"d, mmm")&"]" -> This Month [1 - 30, Jun]
B9: This Quarter | C9: =DATE(YEAR(TODAY()),INT(MONTH(TODAY())/3)+1,1) -> 46082 | D9: =EDATE(C9,4)-1 -> 46203 | E9: =B9&" ["&TEXT(C9,"d mmm")&" - "&TEXT(D9,"d mmm")&"]" -> This Quarter [1 Mar - 30 Jun]
B10: This Year | C10: =DATE(YEAR(TODAY()),1,1) -> 46023 | D10: =EDATE(C10,12)-1 -> 46387 | E10: =B10&" ["&TEXT(C10,"yyyy")&"]" -> This Year [2026]
B11: Interval: | E11: =B11 -> Interval:
B12: Last Week | C12: =C7-7 -> 46181 | D12: =C12+6 -> 46187 | E12: =B12&" ["&TEXT(C12,"d mmm")&" - "&TEXT(D12,"d mmm")&"]" -> Last Week [8 Jun - 14 Jun]
B13: Last Month | C13: =EDATE(C8,-1) -> 46143 | D13: =EDATE(C13,1)-1 -> 46173 | E13: =B13&" ["&TEXT(C13,"d")&" - "&TEXT(D13,"d, mmm")&"]" -> Last Month [1 - 31, May]
B14: Last Quarter | C14: =EDATE(C9,-3) -> 45992 | D14: =EDATE(C14,3)-1 -> 46081 | E14: =B14&" ["&TEXT(C14,"d mmm")&" - "&TEXT(D14,"d mmm")&"]" -> Last Quarter [1 Dec - 28 Feb]
B15: Last Year | C15: =EDATE(C10,-12) -> 45658 | D15: =EDATE(C15,12)-1 -> 46022 | E15: =B15 -> Last Year
B16: Selected Highlight: | C16: =IFERROR(MATCH(HighlightActivities,lstToDoHighlights,0),"") -> 3 | D16: =HighlightActivities -> This Week [15 Jun - 21 Jun] | E16: =ISNUMBER(INDEX($C$5:$C$15,C16)) -> TRUE
B17: Highlight Start | C17: =IFERROR(IF(C16=1,"",IF(E16,INDEX($C$5:$C$15,$C$16),"")),"") -> 46188
B18: Highlight End | C18: =IFERROR(IF(C16=1,"",IF(E16,INDEX($D$5:$D$15,$C$16),"")),"") -> 46194
